{"tx_hash": "31HFcgpUvrdptTzp6NGTQNbu7cF5b3WGcRogok9EmXfW", "action_id_social": "9r5bvDag5sJ2n6SvbKeVxnfUsWNsFnKzDEUz3SXtuhDV-0-widget", "block_id": 87548814, "block_timestamp": "2023-03-18 05:56:01.168", "signer_id": "minorityprogrammers.near", "widget_name": "isNEARAddress", "source_code": "const address = props.address;\nfunction isNearAddress(address) {\n  if (typeof address !== \"string\") {\n    return false;\n  }\n  if (!address.endsWith(\".near\")) {\n    return false;\n  }\n  const parts = address.split(\".\");\n  if (parts.length !== 2) {\n    return false;\n  }\n  if (parts[0].length < 2 || parts[0].length > 32) {\n    return false;\n  }\n  if (!/^[a-z0-9_-]+$/i.test(parts[0])) {\n    return false;\n  }\n  return true;\n}\n", "widget_modules_used": null, "widget_url": "https://near.social/#/minorityprogrammers.near/widget/isNEARAddress", "metadata.description": "Pass in address prop and return boolean based on whether it fits the NEAR account naming convention", "metadata.image.ipfs_cid": "bafkreibfcnevmvmvtv245oj2h2d6ajba2gh65l4killrp4lrxthr6ia6wa", "metadata.linktree.website": "minorityprogrammers.org", "metadata.name": "isNEARAddress Helper Function", "metadata.tags.dev": "", "metadata.tags.helper-function": "", "metadata.tags.utility": "", "branch.draft": null}