{"tx_hash": "2C36nkMBdi1hfmZ5c8KSa4ACXxaS5q4W1BgVyAbRyGDy", "action_id_social": "oxZ5XhaZ16NtDg3v9xeKxik5ejumCVyTiwJ7jw14uHw-0-widget", "block_id": 84855470, "block_timestamp": "2023-02-09 17:29:34.892", "signer_id": "events_v2.near", "widget_name": "event_lists__index__list__big", "source_code": "const { event_lists } = props;\nif (!event_lists) {\n  return props.__engine.helpers.propIsRequiredMessage('event_lists');\n}\n\nconst GRID_PAD = props.__engine.Constants.GRID_PAD;\nconst ListWrapper = styled.div`\n  margin-bottom: ${GRID_PAD};\n  width: 100%;\n`;\n\nreturn (\n  <>\n    {event_lists.map((event_list, idx) => {\n      return (\n        <ListWrapper key={`${idx}-${event_list.event_list_id}`}>\n          {props.__engine.renderComponent('index.list.item', {\n            event_list,\n            include_events: true,\n          })}\n        </ListWrapper>\n      );\n    })}\n  </>\n);\n", "metadata": null, "branch": null, "widget_modules_used": null, "widget_url": "https://near.social/#/events_v2.near/widget/event_lists__index__list__big"}