{"tx_hash": "CUbGjMwrEM5BPy95YZ1X2rJyorhxNYSM8tqzAKSvxYmF", "action_id_social": "8d12RtXVnFxD1qqJLEPX1fqAv8ZWxAQP88oi4WdwS7yu-0-widget", "block_id": 85733780, "block_timestamp": "2023-02-21 17:42:03.065", "signer_id": "calebjacob.near", "widget_name": "Comments.Feed", "source_code": "const index = {\n  action: \"comment\",\n  key: props.item,\n  options: {\n    limit: props.limit ?? 5,\n    order: \"desc\",\n    accountId: props.accounts,\n    subscribe: props.subscribe,\n  },\n};\n\nconst raw = !!props.raw;\n\nconst Wrapper = styled.div`\n  > div:first-child {\n    a {\n      display: inline-flex;\n      margin-bottom: 12px;\n      font-size: 14px;\n      line-height: 20px;\n      color: #687076;\n      outline: none;\n      font-weight: 600;\n\n      &:hover,\n      &:focus {\n        color: #687076;\n        text-decoration: underline;\n      }\n    }\n  }\n`;\n\nconst renderItem = (a) =>\n  a.value.type === \"md\" && (\n    <div key={JSON.stringify(a)}>\n      <Widget\n        src=\"calebjacob.near/widget/Comments.Comment\"\n        props={{\n          accountId: a.accountId,\n          blockHeight: a.blockHeight,\n          highlight:\n            a.accountId === props.highlightComment?.accountId &&\n            a.blockHeight === props.highlightComment?.blockHeight,\n          raw,\n        }}\n      />\n    </div>\n  );\n\nreturn (\n  <Wrapper>\n    <Widget\n      src=\"mob.near/widget/ManualIndexFeed\"\n      props={{\n        index,\n        reverse: true,\n        renderItem,\n        nextLimit: 10,\n        loadMoreText: \"Show earlier comments...\",\n      }}\n    />\n  </Wrapper>\n);\n", "metadata": null, "branch": NaN, "widget_modules_used": null, "widget_url": "https://near.social/#/calebjacob.near/widget/Comments.Feed", "branch.draft.": NaN, "branch.draft.metadata": NaN, "branch.draft": NaN}