{"tx_hash": "3qSySb3p7UZh5ViYT5Drz42doqcHGNVd9UfP8ovmwk5n", "action_id_social": "JCg4hurSmRiiaubPiR4tkNinbqH8HjncDagzGvtpHLg7-0-widget", "block_id": 94786593, "block_timestamp": "2023-06-22T18:43:09.505Z", "signer_id": "efiz.near", "widget_name": "marquee", "source_code": "const text = props.text ?? \"Hello World\";\nconst fontFamily = props.fontFamily ?? \"Arial, sans-serif\";\nconst fontSize = props.fontSize ?? \"20px\";\nconst textColor = props.textColor ?? \"white\";\nconst backgroundColor = props.backgroundColor ?? \"black\";\nconst height = props.height ?? \"60px\";\nconst width = props.width ?? \"100%\";\n\nconst code = `\n    <style>\n      body {\n        margin: 0\n      }\n\n      .marquee {\n        white-space: nowrap;\n        overflow: hidden;\n        position: relative;\n        color: ${textColor};\n        background-color: ${backgroundColor};\n        font-family: ${fontFamily};\n        font-size: ${fontSize};\n        height: ${height};\n        width: ${width};\n        display: flex;\n        align-items: center;\n        justify-content: start;\n      }\n\n      .marquee span {\n        display: inline-block;\n        padding-left: 100%;\n        animation: marquee 15s linear infinite;\n      }\n\n      @keyframes marquee {\n        0% { transform: translate(0, 0); }\n        100% { transform: translate(-100%, 0); }\n      }\n    </style>\n\n    <div class=\"marquee\">\n      <span>${text}</span>\n    </div>\n  `;\n\nreturn <iframe className=\"w-100\" srcDoc={code} />;\n", "metadata": null, "branch": null, "widget_modules_used": null, "widget_url": "https://near.social/#/efiz.near/widget/marquee", "__row_index": 0}