{"tx_hash": "ABgJEuLUjcuKdi6wyyeDVEeFnW4yS4iMBSLviUcbPWEA", "action_id_social": "HT8Ni82yNDupFPcEDRniLRkSZ2QWSoGKU9tfLhsX1V75-0-widget", "block_id": 88684426, "block_timestamp": "2023-04-02 23:39:11.450", "signer_id": "weige.near", "widget_name": "ref-swap-button", "source_code": "const { accountId, notEnough, canSwap, callTx } = props;\n\nconst ButtonWrapper = styled.button`\n  \n  border-radius: 12px;\n\n  background-color: ${(props) =>\n    props.notEnough ? \"rgba(255,136,179, 0.5)\" : \"rgba(0,255,209,1)\"};\n  font-weight: 700;\n  font-size: 18px;\n  cursor: ${(props) => (props.disabled ? \"not-allowed\" : \"pointer\")}\n  color:black;\n  width: 100%;\n  display: flex;\n  align-items:center;\n  justify-content: center;\n  outline:none;\n  border:none;\n  padding: 8px 0px;\n  margin-top: 26px\n`;\n\nreturn (\n  <ButtonWrapper\n    notEnough={notEnough}\n    disabled={!canSwap || notEnough}\n    onClick={() => {\n      if (!canSwap || notEnough) return;\n\n      callTx();\n    }}\n  >\n    {!accountId\n      ? \"Connect wallet\"\n      : notEnough\n      ? \"Insufficient Balance\"\n      : \"Swap\"}\n  </ButtonWrapper>\n);\n", "metadata": null, "branch": null, "widget_modules_used": null, "widget_url": "https://near.social/#/weige.near/widget/ref-swap-button"}