{"tx_hash": "EFttET1TCgFJFET7DrhZTmWP6UKsHSCjAQ43b9X9wstk", "action_id_social": "E37rUQDdQfKfNP7aXtKyefzSWKXLE77B6JhHiiFRVB25-0-widget", "block_id": 91064584, "block_timestamp": "2023-05-04 08:04:46.742", "signer_id": "nearhorizon.near", "widget_name": "Project.People", "source_code": "const ownerId = \"nearhorizon.near\";\nconst accountId = props.accountId ?? context.accountId;\n\nState.init({\n  founders: null,\n  foundersIsFetched: false,\n  team: null,\n  teamIsFetched: false,\n});\n\nif (!state.foundersIsFetched) {\n  Near.asyncView(\n    ownerId,\n    \"get_founders\",\n    { account_id: accountId },\n    \"final\",\n    false\n  ).then((founders) => State.update({ founders, foundersIsFetched: true }));\n}\n\nif (!state.teamIsFetched) {\n  Near.asyncView(\n    ownerId,\n    \"get_team\",\n    { account_id: accountId },\n    \"final\",\n    false\n  ).then((team) => State.update({ team, teamIsFetched: true }));\n}\n\nif (!state.namesIsFetched) {\n  Near.asyncView(\n    \"social.near\",\n    \"get\",\n    {\n      keys: [...state.founders, ...state.team].map(\n        (key) => `${key}/profile/name`\n      ),\n    },\n    \"final\",\n    false\n  ).then((names) => {\n    State.update({\n      names: new Map(\n        Object.keys(names).map((account) => [\n          account,\n          names[account].profile.name,\n        ])\n      ),\n      namesIsFetched: true,\n    });\n  });\n}\n\nif (!state.foundersIsFetched || !state.teamIsFetched || !state.namesIsFetched) {\n  return <>Loading...</>;\n}\n\nconst List = styled.ul`\n  display: flex;\n  flex-direction: column;\n  gap: 1em;\n  padding: 0;\n  margin: 0;\n  list-style: none;\n  width: 100%;\n`;\n\nconst Item = styled.li`\n  display: flex;\n  flex-direction: row;\n  gap: 1em;\n  align-items: center;\n  justify-content: flex-start;\n  width: 100%;\n  padding: 1.5em 0px;\n  border-bottom: 1px solid #eaecf0;\n`;\n\nconst Heading = styled.h3`\n  font-style: normal;\n  font-weight: 700;\n  font-size: 1.125em;\n  line-height: 1.5em;\n  margin-top: 1em;\n\n  color: #000000;\n`;\n\nconst Container = styled.div`\n  width: 100%;\n`;\n\nreturn (\n  <Container>\n    <Heading>Founders</Heading>\n    <List>\n      {state.founders.map((founder) => (\n        <Item>\n          <Widget\n            src={`${ownerId}/widget/Vendor.Icon`}\n            props={{ accountId: founder, size: \"2em\" }}\n          />\n          <Widget\n            src={`${ownerId}/widget/NameAndAccount`}\n            props={{\n              accountId: founder,\n              name: state.names.get(founder),\n              nameSize: \".9em\",\n            }}\n          />\n        </Item>\n      ))}\n    </List>\n    <Heading>Team</Heading>\n    <List>\n      {state.team.map((member) => (\n        <Item>\n          <Widget\n            src={`${ownerId}/widget/Vendor.Icon`}\n            props={{ accountId: member, size: \"2em\" }}\n          />\n          <Widget\n            src={`${ownerId}/widget/NameAndAccount`}\n            props={{\n              accountId: member,\n              name: state.names.get(member),\n              nameSize: \".9em\",\n            }}\n          />\n        </Item>\n      ))}\n    </List>\n  </Container>\n);\n", "metadata": null, "branch": null, "widget_modules_used": null, "widget_url": "https://near.social/#/nearhorizon.near/widget/Project.People"}