{"tx_hash": "5eqT2KFjvNe3ZufpS6VT3VP1DbMtCngmctNEtByw87w6", "action_id_social": "AvM1miUhULisJNrC43KxH1WCiRC59Xb7ugRvxDWWPRbc-0-widget", "block_id": 90402687, "block_timestamp": "2023-04-25 14:13:40.805", "signer_id": "frichard5.near", "widget_name": "NDC-checkbox-list", "source_code": "const { checkboxes, label, updateChecked, selectedBoxes } = props;\n\nState.init({\n  checkboxes,\n  title,\n});\n\nconst Input = styled.input``;\nconst Fieldset = styled.fieldset`\n    display: flex;\n    flex-direction: column;\n`;\n\nconst handleChange = (e) => {\n  if (e.target.checked) {\n    updateChecked([...selectedBoxes, e.target.value]);\n  } else {\n    const selectedList = selectedBoxes.filter((b) => b != e.target.value);\n    updateChecked(selectedList);\n  }\n};\n\nreturn (\n  <Fieldset>\n    <p>{label}</p>\n    {state.checkboxes.map((c) => {\n      console.log(c.value, c.selected);\n      return (\n        <label>\n          <input\n            className=\"\"\n            type=\"checkbox\"\n            value={c.value}\n            onChange={handleChange}\n            selected={selectedBoxes.includes(c.value)}\n          />\n          {c.label}\n        </label>\n      );\n    })}\n  </Fieldset>\n);\n", "metadata": null, "branch": null, "widget_modules_used": null, "widget_url": "https://near.social/#/frichard5.near/widget/NDC-checkbox-list"}