{"tx_hash": "3ukVhmfpFJ3cF4gjHEYvSxoRcoBgfRht3yWLaWBN9nu5", "action_id_social": "BFz9KFZhj5PwmGQZUHANS3BPT63krRwtSmgcZuF2HUva-0-widget", "block_id": 94250964, "block_timestamp": "2023-06-15T16:27:25.546Z", "signer_id": "neardigitalcollective.near", "widget_name": "EasyPoll.Voting2", "source_code": "const FlexContainer = styled.div`\n    display:flex;\n    @media screen and (max-width: 768px)  {\n      display: block;\n      padding: 1rem;\n    }\n`;\n\nconst VotingContainer = styled.div`\n    width: 75%;\n    margin: 2rem 0.5rem 2rem 2rem;\n    padding: 2rem;\n    @media screen and (max-width: 768px)  {\n      width: 100%;\n      margin: 0rem;\n    }\n`;\n\nconst NoFlexInMobile = styled.div`\n  display:flex;\n   @media screen and (max-width: 768px)  {\n     display: block;\n    }\n`;\n\nconst widgetOwner = \"neardigitalcollective.near\";\nconst indexVersion = props.indexVersion ?? \"3.2.0\";\nconst whitelist = props.whitelist;\n\nreturn (\n  <div>\n    <FlexContainer className=\"content-align-start justify-content-between\">\n      <VotingContainer\n        style={{\n          borderRadius: \"18px\",\n          background: \"white\",\n          boxShadow: \"0px 8px 28px rgba(43, 68, 106, 0.05)\",\n        }}\n      >\n        <NoFlexInMobile className=\"justify-content-between\">\n          <NoFlexInMobile>\n            <div>\n              <p style={{ margin: \"0\", fontWeight: \"300\" }}>Created by</p>\n              <p style={{ fontWeight: \"500\" }}>\n                {props.sliceString(props.state.poll.accountId, 18)}\n              </p>\n            </div>\n          </NoFlexInMobile>\n\n          {Date.now() < props.state.poll.value.endTimestamp && (\n            <>\n              <span>\n                Started{\" \"}\n                {new Date(\n                  props.state.poll.value.startTimestamp\n                ).toLocaleDateString()}\n              </span>\n\n              <span\n                style={{\n                  paddingLeft: \"1.5rem\",\n                  borderLeft: \"2px solid #ced4da\",\n                  height: \"max-content\",\n                }}\n              >\n                Ends\n                <Widget\n                  src={`silkking.near/widget/timeAgo`}\n                  props={{\n                    timeInFuture: props.state.poll.value.endTimestamp,\n                    reduced: true,\n                  }}\n                />\n              </span>\n            </>\n          )}\n          <span\n            style={{\n              backgroundColor: props.isUpcoming(props.state.poll)\n                ? \"#FFF3B4\"\n                : props.isActive(props.state.poll)\n                ? \"#D9FCEF\"\n                : \"#FFE5E5\",\n\n              height: \"2.1rem\",\n              width: \"5rem\",\n              textAlign: \"center\",\n              borderRadius: \"16px\",\n              marginRight: \"1rem\",\n              lineHeight: \"1.9rem\",\n              fontSize: \"1rem\",\n              letterSpacing: \"-0.025rem\",\n              color: props.isUpcoming(props.state.poll)\n                ? \"#FFC905\"\n                : props.isActive(props.state.poll)\n                ? \"#00B37D\"\n                : \"#FF4747\",\n              fontWeight: \"500\",\n            }}\n          >\n            {props.isUpcoming(props.state.poll)\n              ? \"Upcoming\"\n              : props.isActive(props.state.poll)\n              ? \"Active\"\n              : \"Closed\"}\n          </span>\n        </NoFlexInMobile>\n        <div className=\"d-flex my-3\">\n          <div\n            style={{\n              height: \"inherit\",\n              backgroundColor: \"#AAC8F7\",\n              width: \"0.5rem\",\n              minWidth: \"5px\",\n              marginRight: \"0.5rem\",\n              borderRadius: \"8px\",\n            }}\n          >\n            {/*Decorative div, do not delete*/}\n          </div>\n          <h2\n            style={{\n              fontWeight: \"700\",\n              fontSize: \"2rem\",\n              letterSpacing: \"0.1px\",\n              color: \"#010A2D\",\n              wordWrap: \"anywhere\",\n            }}\n          >\n            {props.state.poll.value.title}\n          </h2>\n        </div>\n        <div\n          style={{\n            position: \"relative\",\n            width: \"max-content\",\n            margin: \"1rem\",\n          }}\n        >\n          <Widget\n            src={`${widgetOwner}/widget/EasyPoll.Share`}\n            props={{ blockHeight: props.questionBlockHeight }}\n          />\n        </div>\n        <div\n          className=\"p-3\"\n          style={{\n            position: \"relative\",\n            border: \"1.5px solid rgb(206, 212, 218)\",\n            borderRadius: \"24px\",\n            wordWrap: \"anywhere\",\n          }}\n        >\n          <h3\n            style={{\n              fontWeight: \"700\",\n              fontSize: \"1.2rem\",\n              marginBottom: \"1.2rem\",\n            }}\n          >\n            Description\n          </h3>\n          <p style={{ fontSize: \"0.9rem\" }}>\n            {props.showDescription(props.state.poll.value.description)}\n          </p>\n          {props.state.poll.value.description.length > 501 &&\n          !props.state.descriptionHeightLimited ? (\n            <div\n              style={{\n                position: \"absolute\",\n                bottom: \"-1.125rem\",\n                left: \"0\",\n                right: \"0\",\n                marginRight: \"auto\",\n                marginLeft: \"auto\",\n                textAlign: \"center\",\n              }}\n            >\n              <h4\n                style={{\n                  fontSize: \"1.2rem\",\n                  display: \"inline-block\",\n                  backgroundColor: \"white\",\n                  padding: \"0 1rem\",\n                  cursor: \"pointer\",\n                }}\n                onClick={() =>\n                  props.stateUpdate({ descriptionHeightLimited: true })\n                }\n              >\n                Show less <i className=\"bi bi-arrow-up\"></i>\n              </h4>\n            </div>\n          ) : (\n            props.state.poll.value.description.length > 501 && (\n              <div\n                style={{\n                  position: \"absolute\",\n                  bottom: \"-1.125rem\",\n                  left: \"0\",\n                  right: \"0\",\n                  marginRight: \"auto\",\n                  marginLeft: \"auto\",\n                  textAlign: \"center\",\n                }}\n              >\n                <h4\n                  style={{\n                    fontSize: \"1.2rem\",\n                    display: \"inline-block\",\n                    backgroundColor: \"white\",\n                    padding: \"0 1rem\",\n                    cursor: \"pointer\",\n                  }}\n                  onClick={() =>\n                    props.stateUpdate({ descriptionHeightLimited: false })\n                  }\n                >\n                  Show more <i className=\"bi bi-arrow-down\"></i>\n                </h4>\n              </div>\n            )\n          )}\n        </div>\n        {props.state.poll.value.tgLink != \"\" &&\n          props.state.poll.value.tgLink != undefined && (\n            <div\n              className=\"mt-3 d-flex justify-content-between\"\n              style={{\n                border: \"1.5px solid #D4E5FB\",\n                padding: \"1.2rem 1.7rem\",\n                borderRadius: \"24px\",\n              }}\n            >\n              <div className=\"d-flex\">\n                <i\n                  className=\"bi bi-people d-flex align-items-center justify-content-center\"\n                  style={{\n                    height: \"100%\",\n                    aspectRatio: \"1\",\n                    backgroundColor: \"#2F5BCF\",\n                    borderRadius: \"14px\",\n                    marginRight: \"1rem\",\n                    color: \"white\",\n                  }}\n                ></i>\n                <div>\n                  <p\n                    className=\"m-0\"\n                    style={{\n                      color: \"#2F5BCF\",\n                      fontWeight: \"500\",\n                      fontSize: \"0.7rem\",\n                    }}\n                  >\n                    Discussion link\n                  </p>\n                  <h6>\n                    <a\n                      style={{ color: \"#2346B1\" }}\n                      href={props.state.poll.value.tgLink}\n                    >\n                      {props.sliceString(props.state.poll.value.tgLink, 30)}\n                    </a>\n                  </h6>\n                </div>\n              </div>\n              <div className=\"d-flex align-items-center\">\n                <a\n                  target=\"_blank\"\n                  href={props.state.poll.value.tgLink}\n                  style={{ userSelect: \"none\" }}\n                >\n                  <i\n                    className=\"bi bi-box-arrow-up-right\"\n                    style={{\n                      color: \"#2F5BCF\",\n                      cursor: \"pointer\",\n                    }}\n                  ></i>\n                </a>\n                <i\n                  className=\"bi bi-clipboard\"\n                  style={{\n                    userSelect: \"none\",\n                    color: \"#2F5BCF\",\n                    cursor: \"pointer\",\n                    marginLeft: \"0.8rem\",\n                  }}\n                  onClick={() =>\n                    clipboard.writeText(props.state.poll.value.tgLink)\n                  }\n                ></i>\n              </div>\n            </div>\n          )}\n        {\n          <Widget\n            src={`${widgetOwner}/widget/EasyPoll.DisplayVote`}\n            props={{\n              poll: props.state.poll,\n              isPreview: props.isPreview,\n              indexVersion,\n              whitelist,\n            }}\n          />\n        }\n      </VotingContainer>\n    </FlexContainer>\n    {props.state.showQuestionsByThisUser && props.renderModal()}\n  </div>\n);\n", "metadata": null, "branch": null, "widget_modules_used": null, "widget_url": "https://near.social/#/neardigitalcollective.near/widget/EasyPoll.Voting2", "__row_index": 1}