{"tx_hash": "4mWLmQ3Y3qoaXpoMLiaPVQCZPvt3RnioPVLUZFMnfvZA", "action_id_social": "EohNz9wyGbDmXo8YVWDzteHXuPCCUYQrCLLKg9dLJPCK-0-widget", "block_id": 81053202, "block_timestamp": "2022-12-20 04:33:38.093", "signer_id": "miraclx.near", "widget_name": "Attribution", "source_code": "let authors = props.authors ?? [\"Nobody\"];\n\nfunction humanList(list) {\n  return [list.pop(), list.join(\", \")].filter(Boolean).reverse().join(\" and \");\n}\n\nreturn (\n  <span class=\"text-muted\">\n    By\n    {authors.map((author) => (\n      <a\n        href={`#/mob.near/widget/ProfilePage?accountId=${author}`}\n        class=\"text-muted text-truncate\"\n      >\n        <Widget\n          src=\"mob.near/widget/ProfileLine\"\n          props={{\n            accountId: author,\n            hideAccountId: true,\n            tooltip: true,\n            link: false,\n          }}\n        />\n      </a>\n    ))}\n  </span>\n);\n", "metadata": NaN, "branch": null, "widget_modules_used": null, "widget_url": "https://near.social/#/miraclx.near/widget/Attribution", "metadata.image.ipfs_cid": NaN, "metadata.linktree.website": NaN, "metadata.name": NaN, "metadata.tags.author": NaN, "metadata.tags.credit": NaN, "metadata.tags.profile": NaN, "metadata.description": NaN, "metadata.tags.app": NaN}