{"tx_hash": "2dTqco6SaU8xpWqX96N8LSSMkgkZnUiYqPj3kVNdSxCj", "action_id_social": "Aqdhs4rWD1ALARw4yTup4Zpt6Ns6p9btZminkz5zHPGZ-0-widget", "block_id": 84211896, "block_timestamp": "2023-01-31 14:57:04.649", "signer_id": "events_v1.near", "widget_name": "events__not_found", "source_code": "props.controller.setLayout('modal', {\n  title: 'Alert',\n});\n\nreturn <div>{props.message || 'Not Found'}</div>;\n", "metadata": null, "branch": null, "widget_modules_used": null, "widget_url": "https://near.social/#/events_v1.near/widget/events__not_found"}