{"tx_hash": "Dmj9THaMXpzzvWGDJyrZKNGGqSYVRQU7EwaTzb7xn99v", "action_id_social": "8EzFb26HUU3ysoRVakscPJH4SEqfgnsCHUhskUpUY3wp-0-widget", "block_id": 94688060, "block_timestamp": "2023-06-21T11:39:34.287Z", "signer_id": "williamxx.near", "widget_name": "Creatives.Home.BlackButton", "source_code": "const Link = styled.a`\r\n  display: flex;\r\n  flex-direction: row;\r\n  justify-content: center;\r\n  align-items: center;\r\n  padding: 0.625em 1.25em;\r\n  width: 10.625em;\r\n  gap: 0.5em;\r\n  border: none;\r\n  border-radius: 50px;\r\n  background: #161615;\r\n  color: #fff;\r\n  font-style: normal;\r\n  font-weight: 600;\r\n  font-size: 0.95em;\r\n  line-height: 1em;\r\n  text-align: center;\r\n  white-space: nowrap;\r\n\r\n  &:disabled {\r\n    background: #e5e5e5;\r\n  }\r\n`;\r\n\r\nreturn <Link href={props.href ?? \"#\"}>{props.text}</Link>;\r\n", "metadata": null, "branch": null, "widget_modules_used": null, "widget_url": "https://near.social/#/williamxx.near/widget/Creatives.Home.BlackButton", "__row_index": 0}