{"tx_hash": "FuNpZB4v57TwTHV8aibroNU67o3WNcQ9piDp8Y9SRgHq", "action_id_social": "AaUUJ96V5bBEQD2Kb14sXEqANgUNrCMgxDS5tZs6Lyar-0-widget", "block_id": 92449340, "block_timestamp": "2023-05-22T12:35:50.734Z", "signer_id": "eugenewolf507.near", "widget_name": "WikiOnSocialDB_ArticlesByTag", "source_code": "const addressForArticles = \"wikiTest2Article\";\nconst authorForWidget = \"eugenewolf507.near\";\nconst tagSelected = props.tag;\nconst accountId = props.accountId ?? context.accountId;\nif (!accountId) {\n  return \"No account ID\";\n}\nconst profile = props.profile ?? Social.getr(`${accountId}/profile`);\nif (profile === null) {\n  return \"Loading\";\n}\n\nconst getDateLastEdit = (timestamp) => {\n  const date = new Date(Number(timestamp));\n  const dateString = `${date.toLocaleDateString()} / ${date.toLocaleTimeString()}`;\n  return dateString;\n};\n\n// ========== GET INDEX ARRAY FOR ARTICLES ==========\nconst postsIndex = Social.index(addressForArticles, \"main\", {\n  order: \"desc\",\n  accountId: undefined,\n});\n// ========== GET ALL ARTICLES ==========\nconst resultArticles =\n  postsIndex &&\n  postsIndex.reduce((acc, { accountId, blockHeight }) => {\n    const postData = Social.get(\n      `${accountId}/${addressForArticles}/main`,\n      blockHeight\n    );\n    const postDataWithBlockHeight = { ...JSON.parse(postData), blockHeight };\n    return [...acc, postDataWithBlockHeight];\n  }, []);\n// ========== FILTER DUBLICATES ==========\nconst filteredArticles =\n  resultArticles.length &&\n  resultArticles.reduce((acc, article) => {\n    if (!acc.some(({ articleId }) => articleId === article.articleId)) {\n      return [...acc, article];\n    } else {\n      return acc;\n    }\n  }, []);\n\nconst filteredArticlesByTag =\n  filteredArticles.length &&\n  filteredArticles.reduce((acc, article) => {\n    if (article.tags && article.tags.includes(tagSelected)) {\n      console.log(article);\n      return [...acc, article];\n    } else {\n      return acc;\n    }\n  }, []);\n\nreturn (\n  <>\n    <Widget\n      src={`${authorForWidget}/widget/WikiOnSocialDB_MainNavigation`}\n      props={{ currentNavPill: \"authors\" }}\n    />\n    <div>\n      Tag:\n      {tagSelected}\n    </div>\n    <ol>\n      {filteredArticlesByTag &&\n        filteredArticlesByTag.map((article, index) => (\n          <li key={article.articleId}>\n            <a\n              href={`#/${authorForWidget}/widget/WikiOnSocialDB_OneArticle?articleId=${article.articleId}&blockHeight=${article.blockHeight}&lastEditor=${article.lastEditor}\n            `}\n            >\n              {article.articleId}{\" \"}\n              <small>\n                (last edited:\n                {getDateLastEdit(article.timeLastEdit)})\n              </small>\n            </a>\n            {article.tags.map((tag) => (\n              <a\n                key={tag}\n                href={`/#/${authorForWidget}/widget/WikiOnSocialDB_ArticlesByTag?tag=${tag}`}\n                className=\"me-1 mb-1 text-primary bg-primary bg-opacity-10 position-relative fw-normal badge border border-primary text-decoration-none\"\n              >\n                #{tag}\n              </a>\n            ))}\n          </li>\n        ))}\n    </ol>\n  </>\n);\n", "metadata": null, "branch": null, "widget_modules_used": null, "widget_url": "https://near.social/#/eugenewolf507.near/widget/WikiOnSocialDB_ArticlesByTag", "__row_index": 2}