{"tx_hash": "F9HV1tvg81kAZjXbWeewaFwr1VQ2i9URb4RHH9qmVFfe", "action_id_social": "5XjBe7thtebvK6VMcVCKc9BiYCndUsUkP5VWWjRxRGaM-0-widget", "block_id": 84060749, "block_timestamp": "2023-01-29 13:33:27.318", "signer_id": "events_v1.near", "widget_name": "app__layout_controller", "source_code": "props.__engine.registerLayoutController(props.__ref, (o) => {\n  console.log('LAYOUT CONTROLLER', props.__ref, { o });\n  State.update(o);\n});\n\nState.init({\n  layout: null,\n  layoutProps: null,\n});\n\nif (!state) {\n  return null;\n}\n\nconst layout = state.layout;\nconst layoutProps = state.layoutProps;\n\nfunction renderControl() {\n  // guard to allow 'default' layout exit infinite render loop\n  if (\n    layout === 'default' ||\n    layout === null ||\n    layout === '' ||\n    layout === undefined\n  ) {\n    return (\n      <Widget\n        src={props.__engine.widgetFromName(name)}\n        key={key}\n        props={widgetProps}\n      />\n    );\n  }\n\n  return (\n    <Widget\n      src={layoutFromName(layout)}\n      key={key}\n      props={{\n        ...componentProps,\n        ...(layoutProps || {}),\n        component: {\n          name: name,\n          props: props,\n          layout: innerLayout,\n          layoutProps: innerLayoutProps,\n        },\n      }}\n    />\n  );\n}\n\nreturn renderControl();\n", "metadata": null, "branch": null, "widget_modules_used": null, "widget_url": "https://near.social/#/events_v1.near/widget/app__layout_controller"}