{"tx_hash": "7UQ5FPVjToyvfvyFLEuZqyvY2E2pvdWS1T7KCccrkwm3", "action_id_social": "HdKFKqacGUZyYrEz6vM3Z1Sq8x7eUQfLfGbvMPtyqq48-0-widget", "block_id": 88701821, "block_timestamp": "2023-04-03 05:51:34.937", "signer_id": "create.near", "widget_name": "ABC.Featured", "source_code": "const nearDevGovGigsContractAccountId =\n  props.nearDevGovGigsContractAccountId ||\n  (context.widgetSrc ?? \"devgovgigs.near\").split(\"/\", 1)[0];\nconst nearDevGovGigsWidgetsAccountId =\n  props.nearDevGovGigsWidgetsAccountId ||\n  (context.widgetSrc ?? \"create.near\").split(\"/\", 1)[0];\n\nfunction widget(widgetName, widgetProps, key) {\n  widgetProps = {\n    ...widgetProps,\n    nearDevGovGigsContractAccountId: props.nearDevGovGigsContractAccountId,\n    nearDevGovGigsWidgetsAccountId: props.nearDevGovGigsWidgetsAccountId,\n    referral: props.referral,\n  };\n  return (\n    <Widget\n      src={`create.near/widget/ABC.${widgetName}`}\n      props={widgetProps}\n      key={key}\n    />\n  );\n}\n\nfunction href(widgetName, linkProps) {\n  linkProps = { ...linkProps };\n  if (props.nearDevGovGigsContractAccountId) {\n    linkProps.nearDevGovGigsContractAccountId =\n      props.nearDevGovGigsContractAccountId;\n  }\n  if (props.nearDevGovGigsWidgetsAccountId) {\n    linkProps.nearDevGovGigsWidgetsAccountId =\n      props.nearDevGovGigsWidgetsAccountId;\n  }\n  if (props.referral) {\n    linkProps.referral = props.referral;\n  }\n  const linkPropsQuery = Object.entries(linkProps)\n    .map(([key, value]) => `${key}=${value}`)\n    .join(\"&\");\n  return `#/${nearDevGovGigsWidgetsAccountId}/widget/ABC.${widgetName}${\n    linkPropsQuery ? \"?\" : \"\"\n  }${linkPropsQuery}`;\n}\n\nconst communities = {\n  bodega: {\n    icon: \"https://pbs.twimg.com/profile_images/1633040448175366145/y0afLMb1_400x400.jpg\",\n    cover:\n      \"https://pbs.twimg.com/profile_banners/1591547314384035841/1678182210/1080x360\",\n    title: \"Bodega\",\n    desc: \"Dynamic NFT Launchpad & Trait Marketplace\",\n  },\n  nearweek: {\n    icon: \"https://pbs.twimg.com/profile_images/1590659386132860928/msOLWbog_400x400.jpg\",\n    cover:\n      \"https://pbs.twimg.com/profile_banners/1377963859730911232/1668081831/1500x500\",\n    title: \"NEARWEEK\",\n    desc: \"Ecosystem News & Community Platform\",\n  },\n  \"mr-brown\": {\n    icon: \"https://pbs.twimg.com/profile_images/1500252631704293376/WgOX5tCA_400x400.png\",\n    cover:\n      \"https://pbs.twimg.com/profile_banners/1443067475868860417/1640716128/1080x360\",\n    title: \"Mr. Brown\",\n    desc: \"Thousands of Mr. Brown's Imaginary Selves\",\n  },\n  bluntdao: {\n    icon: \"https://pbs.twimg.com/profile_images/1533663210531958785/nMdK8_mg_400x400.jpg\",\n    cover:\n      \"https://pbs.twimg.com/profile_banners/1486451185804623875/1654488944/1080x360\",\n    title: \"Blunt DAO\",\n    desc: \"IRL Onboarding Movement with Proof of Sesh\",\n  },\n};\n\nreturn (\n  <>\n    <div class=\"h5 pb-3\">Featured Communities</div>\n    <div class=\"row\">\n      {Object.entries(communities).map(([label, community]) => {\n        return (\n          <div class=\"col\">\n            {widget(\n              \"widgets.community.Featured\",\n              {\n                label,\n                ...community,\n              },\n              label\n            )}\n          </div>\n        );\n      })}\n    </div>\n  </>\n);\n", "metadata": null, "branch": null, "widget_modules_used": null, "widget_url": "https://near.social/#/create.near/widget/ABC.Featured"}