{"tx_hash": "8j4tXtCFt5MCkWCHZ5WUrdM1RmLWrvrx9Aj9fxYCv1tg", "action_id_social": "EqRyDur2bjbM2kW1cPNNJdbDdF3TDRMU4YwCJWmctTDz-0-widget", "block_id": 85157145, "block_timestamp": "2023-02-13 18:00:48.243", "signer_id": "events_v2.near", "widget_name": "components__event_date", "source_code": "const event = props.event;\nif (!event) {\n  return <></>;\n}\n\nconst startDate = new Date(event.start_date);\nconst endDate = new Date(event.end_date);\nconst datesAreEqual = startDate.toDateString() === endDate.toDateString();\nconst endDateIsNull =\n  endDate === null || endDate.toDateString() === new Date(0).toDateString();\n\nreturn datesAreEqual ? (\n  <>\n    {startDate.getDate()}{' '}\n    {startDate.toLocaleString('default', { month: 'short' })}{' '}\n    {startDate.getFullYear()}\n  </>\n) : (\n  <>\n    {startDate.getDate()}{' '}\n    {startDate.toLocaleString('default', { month: 'short' })}{' '}\n    {startDate.getFullYear()}\n    {endDateIsNull ? (\n      <> - ongoing</>\n    ) : (\n      <>\n        - {endDate.getDate()}{' '}\n        {endDate.toLocaleString('default', { month: 'short' })}{' '}\n        {endDate.getFullYear()}\n      </>\n    )}\n  </>\n);\n", "metadata": null, "branch": null, "widget_modules_used": null, "widget_url": "https://near.social/#/events_v2.near/widget/components__event_date"}