{"tx_hash": "GiSoK9K31tEf9EAXuWr7ehviZHjYYHUB18o1H82zZe85", "action_id_social": "BvcbVJs6JmTBiR1xp7VTskU1RQ7uiw3HYz65bSiwuGpa-0-widget", "block_id": 88871589, "block_timestamp": "2023-04-05 10:58:07.355", "signer_id": "contribut3.near", "widget_name": "Project.List", "source_code": "const ownerId = \"contribut3.near\";\nconst search = props.search ?? \"\";\n\nState.init({\n  items: [],\n  itemsIsFetched: false,\n});\n\nif (!state.itemsIsFetched) {\n  Near.asyncView(\n    ownerId,\n    \"get_projects\",\n    {},\n    \"final\",\n    false\n  ).then((items) => State.update({ items, itemsIsFetched: true }));\n\n  return <>Loading...</>;\n}\n\nreturn (\n  <Widget\n    src={`${ownerId}/widget/List`}\n    props={{\n      search,\n      items: state.items,\n      createItem: (accountId) => (\n        <Widget src={`${ownerId}/widget/Project.Card`} props={{ accountId }} />\n      ),\n    }}\n  />\n);\n", "metadata": null, "branch": null, "widget_modules_used": null, "widget_url": "https://near.social/#/contribut3.near/widget/Project.List"}