{"tx_hash": "n9PjPwfCQReTGbuzwyUHMrm4QafVb9s8FhabM4qn6KX", "action_id_social": "B4ueEX338BJdVdkZTJG2SeWJFRqHesNkaMjhmhw48w6N-0-widget", "block_id": 88740370, "block_timestamp": "2023-04-03 17:55:07.057", "signer_id": "y3k.near", "widget_name": "Homepage", "source_code": "const accountId = props.debugAccountId ?? context.accountId;\n\n// change this back to !accountId\nif (!accountId) {\n}\n\nconst profile = Social.getr(`${accountId}/profile`);\n\nif (profile === null) {\n  return \"\";\n}\n\nconst name = profile.name;\nconst image = profile.image;\n\nreturn (\n  <div>\n    <div>\n      {accountId && !name && (\n        <div className=\"alert alert-warning rounded-4 mb-3\">\n          <p>Your profile is missing a name.</p>\n          {editProfileButton}\n        </div>\n      )}\n\n      {accountId &&\n        !image.ipfs_cid &&\n        (!image.nft.contractId || !image.nft.tokenId) &&\n        !image.url && (\n          <div className=\"alert alert-warning rounded-4 mb-3\">\n            <p>Your profile is missing a picture.</p>\n            {editProfileButton}\n          </div>\n        )}\n    </div>\n    <div class=\"text-center container\">\n      <div class=\"container\">\n        <div class=\"row  \">\n          <h1 class=\"fw-light\">Monthly Active Accounts</h1>\n\n          <div class=\"row\">\n            <Widget\n              src=\"y3k.near/widget/NEAR-ATLAS-MonthlyActiveAcounts\"\n              props={{}}\n            />\n          </div>\n\n          <div class=\"row\">\n            <div class=\"card shadow-sm bg-dark\">\n              <h1 class=\"fw-light\">NEAR TOP Dapps</h1>\n\n              <Widget src=\"y3k.near/widget/NEAR.ATLAS.REACT.TABLE.TOP.DAPPS\" />\n            </div>\n          </div>\n        </div>\n      </div>\n    </div>\n  </div>\n);\n", "metadata": NaN, "branch": null, "widget_modules_used": null, "widget_url": "https://near.social/#/y3k.near/widget/Homepage", "metadata.name": NaN}