{"tx_hash": "FX7iNMhGzze6quM5e361yKAM5M3Gr9tssQ3BssAAjgP7", "action_id_social": "GCBoe28PHkJ6w7ZegHU5CsZCNg3PTEKRBN2xDuWb9Uqp-0-widget", "block_id": 87807404, "block_timestamp": "2023-03-21 16:33:10.448", "signer_id": "humanman.near", "widget_name": "SimpleCard", "source_code": null, "metadata": NaN, "branch": NaN, "widget_modules_used": null, "widget_url": "https://near.social/#/humanman.near/widget/SimpleCard", "branch.draft.": NaN, "branch.draft": NaN, "metadata.name": "Simple Card Component"}