{"tx_hash": "4rYnioJa8DUnmqcPLpqZJCMMe1DGxZ62wUQzqTMKiNsH", "action_id_social": "4i9puPJn9WVbusxotgCYehXvDvSUBGLw7YeuHrEggJgP-0-widget", "block_id": 94250023, "block_timestamp": "2023-06-15T16:06:35.693Z", "signer_id": "nycdao.near", "widget_name": "projects", "source_code": "const index = {\n  action: \"project\",\n  key: \"nyc\",\n  options: {\n    limit: 9,\n    order: \"desc\",\n    accountId: props.accounts,\n  },\n};\n\nconst renderItem = (a) => {\n  if (a.value.type !== \"md\") {\n    return;\n  }\n\n  return (\n    <div key={JSON.stringify(a)} className=\"my-4\">\n      <Widget\n        src=\"nycdao.near/widget/project.view\"\n        props={{\n          accountId: a.accountId,\n          blockHeight: a.blockHeight,\n        }}\n      />\n    </div>\n  );\n};\n\nreturn <Widget src=\"mob.near/widget/IndexFeed\" props={{ index, renderItem }} />;\n", "metadata": null, "branch": null, "widget_modules_used": null, "widget_url": "https://near.social/#/nycdao.near/widget/projects", "__row_index": 4}