{"tx_hash": "5EnWcCQZgZQMkchA25iwUrF7xpNushA9xLd5mSTqrZoH", "action_id_social": "CK4ohq2xExC4MJwPxopPqRscCQARe9Q2dyVoA9S1K1h-0-widget", "block_id": 89022814, "block_timestamp": "2023-04-07 10:29:18.833", "signer_id": "contribut3.near", "widget_name": "Inputs.Viewable.OneLiner", "source_code": "const ownerId = \"contribut3.near\";\nconst id = props.id ?? \"text\";\nconst label = props.label ?? \"Input\";\nconst value = props.value ?? \"\";\nconst onSave = props.onSave ?? (() => { });\n\nconst LabelArea = styled.div`\n  display: flex;\n  flex-direction: row;\n  align-items: center;\n  justify-content: flex-start;\n  gap: 0.25em;\n`;\n\nconst Input = styled.input`\n  box-sizing: border-box;\n  display: flex;\n  flex-direction: row;\n  align-items: center;\n  padding: 0.5em 0.75em;\n  gap: 0.5em;\n  background: #ffffff;\n  border: 1px solid #d0d5dd;\n  box-shadow: 0px 1px 2px rgba(16, 24, 40, 0.05);\n  border-radius: 4px;\n`;\n\nconst SaveButton = styled.button`\n  display: flex;\n  flex-direction: row;\n  justify-content: center;\n  align-items: center;\n  padding: 0.5em 1em;\n  background: #00ec97;\n  border-radius: 50px;\n  border: none;\n  font-style: normal;\n  font-weight: 600;\n  font-size: 0.95em;\n  line-height: 1em;\n  text-align: center;\n  color: #11181c;\n`;\n\nreturn (\n  <Widget\n    src={`${ownerId}/widget/Inputs.Viewable`}\n    props={{\n      id,\n      label: value,\n      value,\n      edit: (update, v) => (\n        <LabelArea>\n          <Input\n            id\n            type={isLink ? \"url\" : \"text\"}\n            value={v}\n            onChange={(e) => update(e.target.value)}\n          />\n          <SaveButton onClick={() => onSave(v)}>Save</SaveButton>\n        </LabelArea>\n      ),\n      view: <></>,\n    }}\n  />\n);\n", "metadata": null, "branch": null, "widget_modules_used": null, "widget_url": "https://near.social/#/contribut3.near/widget/Inputs.Viewable.OneLiner"}