{"tx_hash": "HAuomuMnWePD6R4F5V6AptVvQECJULaNmSF8Ts179Gfo", "action_id_social": "7D3BfLjYKt6MNt7yC2D4C1P8cpdauuHx3XbipJNzxPvq-0-widget", "block_id": 79050368, "block_timestamp": "2022-11-23 00:46:27.350", "signer_id": "vlad.near", "widget_name": "YoWidget", "source_code": "const accountId = props.accountId ?? \"*\";\n\nconst data = Social.keys(`${accountId}/post/yo`, \"final\", {\n  return_type: \"History\",\n});\n\nif (!data) {\n  return \"Loading\";\n}\n\nconst processData = (data) => {\n  const accounts = Object.entries(data);\n\n  const allItems = accounts\n    .map((account) => {\n      const accountId = account[0];\n      const blockHeights = account[1].post.yo;\n      return blockHeights.map((blockHeight) => ({\n        accountId,\n        blockHeight,\n      }));\n    })\n    .flat();\n\n  allItems.sort((a, b) => b.blockHeight - a.blockHeight);\n  return allItems;\n};\n\nif (JSON.stringify(data) !== JSON.stringify(state.data || {})) {\n  State.update({\n    data,\n    allMemes: processData(data),\n  });\n}\n\nreturn (\n  <div>\n    <CommitButton\n      data={{ post: { yo: \"yo!\" } }}\n      onCommit={() => {\n        State.update({\n          // TODO: Feed needs reload?\n        });\n      }}\n    >\n      yo!\n    </CommitButton>\n\n    {data ? state.allItems.map((yo) => <div>{yo}</div>) : \"Loading\"}\n  </div>\n);\n", "metadata": NaN, "branch": null, "widget_modules_used": null, "widget_url": "https://near.social/#/vlad.near/widget/YoWidget", "metadata.description": NaN, "metadata.name": NaN, "metadata.tags.app": NaN, "metadata.tags.yo": NaN, "metadata.image.ipfs_cid": NaN}