{"tx_hash": "HRb6b4k77CAD1uUqtcjz2bHMSj5A8GgXjD9Jyy12PfFw", "action_id_social": "8SyZYmg3aAptZfKVncFgRVcc9AG2VJBUjW3vC2WVoDQ3-1-widget", "block_id": 80605963, "block_timestamp": "2022-12-14 04:21:05.629", "signer_id": "lewidenmann.near", "widget_name": "deer", "source_code": "function moreDeer() {\n  let deer = [];\n  for (let i = 0; i < 1000; i++) {\n    deer.push(\"https://i.giphy.com/media/Qld1cd6a6QlWw/giphy.webp\");\n  }\n  return deer;\n}\n\nState.init({\n  deer: moreDeer(),\n});\n\nfunction loadMoreDeer() {\n  State.update({\n    deer: state.deer.concat(moreDeer()),\n  });\n}\n\nreturn (\n  <div class=\"\">\n    <InfiniteScroll\n      pageStart={0}\n      loadMore={loadMoreDeer}\n      hasMore={true}\n      loader={<p>deer...</p>}\n    >\n      {state.deer.map((url, index) => (\n        <img src={url} />\n      ))}\n    </InfiniteScroll>\n  </div>\n);\n", "branch": null, "widget_modules_used": null, "widget_url": "https://near.social/#/lewidenmann.near/widget/deer", "metadata.image.url": NaN, "metadata.name": NaN, "metadata.tags.deer": NaN, "metadata": NaN}