{"tx_hash": "7dgdgZ5EBereAEPT1yMwgEZnmLJcEV2ujuMtBUcoCq98", "action_id_social": "ErGoF3tUunb7DF5qBukZyKVrk5XkCExGJURZoWs8doxU-0-widget", "block_id": 84694135, "block_timestamp": "2023-02-07 11:58:02.559", "signer_id": "events_v2.near", "widget_name": "layouts__loading", "source_code": "const AlertContent = styled.div`\n  top: 50%;\n  left: 50%;\n  position: absolute;\n  transform-origin: bottom left;\n  background-color: white;\n  width: 50%;\n  height: 50%;\n  max-width: 200px;\n  max-height: 200px;\n  border-radius: 12px;\n  box-shadow: 0 0 40px -10px rgba(0, 0, 0, 0.5);\n  transform: translate(-50%, -50%);\n`;\n\nreturn (\n  <>\n    <div\n      style={{\n        position: 'fixed',\n        top: 0,\n        left: 0,\n        right: 0,\n        bottom: 0,\n        zIndex: 1000,\n        overflow: 'hidden',\n      }}\n    >\n      <AlertContent>\n        {props.__engine.renderComponent(\n          props.component.name,\n          props.component.props\n        )}\n      </AlertContent>\n    </div>\n  </>\n);\n", "metadata": null, "branch": null, "widget_modules_used": null, "widget_url": "https://near.social/#/events_v2.near/widget/layouts__loading"}